odoo/addons/purchase_representative/README.rst
odoo/addons/purchase_representative/__init__.py
odoo/addons/purchase_representative/__manifest__.py
odoo/addons/purchase_representative/i18n/purchase_representative.pot
odoo/addons/purchase_representative/models/__init__.py
odoo/addons/purchase_representative/models/stock_rule.py
odoo/addons/purchase_representative/readme/CONTRIBUTORS.rst
odoo/addons/purchase_representative/readme/DESCRIPTION.rst
odoo/addons/purchase_representative/readme/USAGE.rst
odoo/addons/purchase_representative/static/description/icon.png
odoo/addons/purchase_representative/static/description/index.html
odoo13_addon_purchase_representative-13.0.1.0.1.dev3.dist-info/METADATA
odoo13_addon_purchase_representative-13.0.1.0.1.dev3.dist-info/WHEEL
odoo13_addon_purchase_representative-13.0.1.0.1.dev3.dist-info/top_level.txt
odoo13_addon_purchase_representative-13.0.1.0.1.dev3.dist-info/RECORD
